flask_i18n_pro/__init__.py
flask_i18n_pro/formatters.py
flask_i18n_pro/locale_selector.py
flask_i18n_pro/time_utils.py
flask_i18n_pro-1.0.0.dist-info/licenses/LICENSE
flask_i18n_pro-1.0.0.dist-info/METADATA
flask_i18n_pro-1.0.0.dist-info/WHEEL
flask_i18n_pro-1.0.0.dist-info/top_level.txt
flask_i18n_pro-1.0.0.dist-info/RECORD
