Metadata-Version: 2.4
Name: flask-i18n-pro
Version: 1.0.0
Summary: Production-grade i18n for Flask with Cyrillic and Asian language support
Home-page: https://github.com/wallmarkets/flask-i18n-pro
Author: wallmarkets Team
Author-email: team@wallmarkets.store
Project-URL: Bug Reports, https://github.com/wallmarkets/flask-i18n-pro/issues
Project-URL: Source, https://github.com/wallmarkets/flask-i18n-pro
Project-URL: Documentation, https://github.com/wallmarkets/flask-i18n-pro#readme
Keywords: flask i18n internationalization localization babel cyrillic russian mongolian chinese translation
Classifier: Development Status :: 5 - Production/Stable
Classifier: Intended Audience :: Developers
Classifier: License :: OSI Approved :: MIT License
Classifier: Operating System :: OS Independent
Classifier: Programming Language :: Python :: 3
Classifier: Programming Language :: Python :: 3.7
Classifier: Programming Language :: Python :: 3.8
Classifier: Programming Language :: Python :: 3.9
Classifier: Programming Language :: Python :: 3.10
Classifier: Programming Language :: Python :: 3.11
Classifier: Framework :: Flask
Classifier: Topic :: Software Development :: Libraries :: Python Modules
Classifier: Topic :: Software Development :: Internationalization
Classifier: Natural Language :: English
Classifier: Natural Language :: Russian
Classifier: Natural Language :: Chinese (Simplified)
Requires-Python: >=3.7
License-File: LICENSE
Requires-Dist: Flask>=2.0.0
Requires-Dist: Flask-Babel>=2.0.0
Requires-Dist: Babel>=2.9.0
Provides-Extra: dev
Requires-Dist: pytest>=7.0.0; extra == "dev"
Requires-Dist: pytest-cov>=3.0.0; extra == "dev"
Requires-Dist: black>=22.0.0; extra == "dev"
Requires-Dist: flake8>=4.0.0; extra == "dev"
Dynamic: author
Dynamic: author-email
Dynamic: classifier
Dynamic: description
Dynamic: description-content-type
Dynamic: home-page
Dynamic: keywords
Dynamic: license-file
Dynamic: project-url
Dynamic: provides-extra
Dynamic: requires-dist
Dynamic: requires-python
Dynamic: summary
